{
  "data": {
    "stocks": [
      {
        "symbol": "NVDA",
        "name": "NVIDIA Corp",
        "sector": "Unknown",
        "industry": "Unknown",
        "lastPrice": 190.9,
        "changePercent": 0.5689600674323109,
        "marketCap": 4612626000000,
        "peRatio": 46.4991834513,
        "pbRatio": 38.7951420137,
        "dividendYield": 0,
        "popularityScore": 50
      },
      {
        "symbol": "AAPL",
        "name": "Apple Inc",
        "sector": "Unknown",
        "industry": "Unknown",
        "lastPrice": 262.9,
        "changePercent": -0.6349686295260438,
        "marketCap": 3909527476740,
        "peRatio": 33.1943204254,
        "pbRatio": 44.3307345134,
        "dividendYield": 0,
        "popularityScore": 50
      },
      {
        "symbol": "GOOGL",
        "name": "Alphabet Inc - Class A",
        "sector": "Unknown",
        "industry": "Unknown",
        "lastPrice": 317.22,
        "changePercent": 0.7111562638897736,
        "marketCap": 3800863660000,
        "peRatio": 28.7573856397,
        "pbRatio": 9.1528630152,
        "dividendYield": 0,
        "popularityScore": 50
      },
      {
        "symbol": "MSFT",
        "name": "Microsoft Corporation",
        "sector": "Unknown",
        "industry": "Unknown",
        "lastPrice": 395.07,
        "changePercent": -0.5437655766180864,
        "marketCap": 2952363375895.65,
        "peRatio": 24.7552730618,
        "pbRatio": 7.5532161839,
        "dividendYield": 0,
        "popularityScore": 50
      },
      {
        "symbol": "AMZN",
        "name": "Amazon.com Inc",
        "sector": "Unknown",
        "industry": "Unknown",
        "lastPrice": 207.99,
        "changePercent": -1.0089952881823827,
        "marketCap": 2246121286071.21,
        "peRatio": 28.9187754097,
        "pbRatio": 5.4641511344,
        "dividendYield": 0,
        "popularityScore": 50
      },
      {
        "symbol": "META",
        "name": "Meta Platforms Inc - Class A",
        "sector": "Unknown",
        "industry": "Unknown",
        "lastPrice": 650.3,
        "changePercent": -0.8174968733794976,
        "marketCap": 1652609124249.02,
        "peRatio": 27.3348295387,
        "pbRatio": 7.6071915977,
        "dividendYield": 0,
        "popularityScore": 50
      },
      {
        "symbol": "AVGO",
        "name": "Broadcom Inc",
        "sector": "Unknown",
        "industry": "Unknown",
        "lastPrice": 330.98,
        "changePercent": -0.5020291597775317,
        "marketCap": 1570894724568.3,
        "peRatio": 67.9276452723,
        "pbRatio": 19.3240998446,
        "dividendYield": 0,
        "popularityScore": 50
      },
      {
        "symbol": "TSLA",
        "name": "Tesla Inc",
        "sector": "Unknown",
        "industry": "Unknown",
        "lastPrice": 407.28,
        "changePercent": -1.1024233888592152,
        "marketCap": 1369638849353.94,
        "peRatio": 361.0012781639,
        "pbRatio": 16.6750532568,
        "dividendYield": 0,
        "popularityScore": 50
      },
      {
        "symbol": "WMT",
        "name": "Walmart Inc",
        "sector": "Unknown",
        "industry": "Unknown",
        "lastPrice": 122.99,
        "changePercent": -1.5055657884199645,
        "marketCap": 980580959494.78,
        "peRatio": 42.801438651,
        "pbRatio": 10.2043931931,
        "dividendYield": 0,
        "popularityScore": 50
      },
      {
        "symbol": "LLY",
        "name": "Lilly(Eli) & Company",
        "sector": "Unknown",
        "industry": "Unknown",
        "lastPrice": 1054,
        "changePercent": 4.406054362469295,
        "marketCap": 954383810366.64,
        "peRatio": 46.2395256961,
        "pbRatio": 35.9669798518,
        "dividendYield": 0,
        "popularityScore": 50
      },
      {
        "symbol": "JPM",
        "name": "JPMorgan Chase & Company",
        "sector": "Unknown",
        "industry": "Unknown",
        "lastPrice": 308.81,
        "changePercent": -0.6370861353325455,
        "marketCap": 846051898663.05,
        "peRatio": 15.1948976053,
        "pbRatio": 2.334335524,
        "dividendYield": 0,
        "popularityScore": 50
      },
      {
        "symbol": "XOM",
        "name": "Exxon Mobil Corp",
        "sector": "Unknown",
        "industry": "Unknown",
        "lastPrice": 147.73,
        "changePercent": 0.30554046713741756,
        "marketCap": 621104151629.92,
        "peRatio": 21.5332184035,
        "pbRatio": 2.3945168653,
        "dividendYield": 0,
        "popularityScore": 50
      },
      {
        "symbol": "V",
        "name": "Visa Inc - Class A",
        "sector": "Unknown",
        "industry": "Unknown",
        "lastPrice": 320.95,
        "changePercent": 0.6333678236603586,
        "marketCap": 593458679866.778,
        "peRatio": 28.5426452418,
        "pbRatio": 15.304398996,
        "dividendYield": 0,
        "popularityScore": 50
      },
      {
        "symbol": "JNJ",
        "name": "Johnson & Johnson",
        "sector": "Unknown",
        "industry": "Unknown",
        "lastPrice": 242.63,
        "changePercent": 0.05773433956038861,
        "marketCap": 584229969283.98,
        "peRatio": 21.7963725296,
        "pbRatio": 7.164597877,
        "dividendYield": 0,
        "popularityScore": 50
      },
      {
        "symbol": "MA",
        "name": "Mastercard Inc.",
        "sector": "Financial Services",
        "industry": "Unknown",
        "lastPrice": 526.41,
        "changePercent": 1.1821012570637714,
        "marketCap": 472713994345.68,
        "peRatio": 31.581640456,
        "pbRatio": 61.0978408098,
        "dividendYield": 0,
        "popularityScore": 50
      },
      {
        "symbol": "COST",
        "name": "Costco Wholesale Corp",
        "sector": "Unknown",
        "industry": "Unknown",
        "lastPrice": 985.27,
        "changePercent": -0.2581441963110757,
        "marketCap": 436651146737.52,
        "peRatio": 52.5958981857,
        "pbRatio": 14.4095022518,
        "dividendYield": 0,
        "popularityScore": 50
      },
      {
        "symbol": "ORCL",
        "name": "Oracle Corp",
        "sector": "Unknown",
        "industry": "Unknown",
        "lastPrice": 145.91,
        "changePercent": -1.4654240950837492,
        "marketCap": 420801009120,
        "peRatio": 27.2804544,
        "pbRatio": 14.0496480625,
        "dividendYield": 0,
        "popularityScore": 50
      },
      {
        "symbol": "ABBV",
        "name": "Abbvie Inc",
        "sector": "Unknown",
        "industry": "Unknown",
        "lastPrice": 224.81,
        "changePercent": 0.20503677289949096,
        "marketCap": 397325739119.92,
        "peRatio": 94.0193419593,
        "pbRatio": -121.5063422385,
        "dividendYield": 0,
        "popularityScore": 50
      },
      {
        "symbol": "BAC",
        "name": "Bank Of America Corp",
        "sector": "Unknown",
        "industry": "Unknown",
        "lastPrice": 53.06,
        "changePercent": 0.5495546712147037,
        "marketCap": 393012624374.72,
        "peRatio": 13.9099817504,
        "pbRatio": 1.2921586061,
        "dividendYield": 0,
        "popularityScore": 50
      },
      {
        "symbol": "HD",
        "name": "Home Depot Inc",
        "sector": "Unknown",
        "industry": "Unknown",
        "lastPrice": 382.25,
        "changePercent": 0.9694120133129104,
        "marketCap": 380486545815.75,
        "peRatio": 26.0928916346,
        "pbRatio": 31.4036435965,
        "dividendYield": 0,
        "popularityScore": 50
      },
      {
        "symbol": "PG",
        "name": "Procter & Gamble Company",
        "sector": "Unknown",
        "industry": "Unknown",
        "lastPrice": 160.65,
        "changePercent": -0.08085582783928066,
        "marketCap": 375700020008.22,
        "peRatio": 22.8347426006,
        "pbRatio": 7.0832001661,
        "dividendYield": 0,
        "popularityScore": 50
      },
      {
        "symbol": "GE",
        "name": "General Electric Company",
        "sector": "Unknown",
        "industry": "Unknown",
        "lastPrice": 342.78,
        "changePercent": -0.12819765747918377,
        "marketCap": 362033230533.42,
        "peRatio": 41.5938913756,
        "pbRatio": 19.3839069729,
        "dividendYield": 0,
        "popularityScore": 50
      },
      {
        "symbol": "CAT",
        "name": "Caterpillar Inc",
        "sector": "Unknown",
        "industry": "Unknown",
        "lastPrice": 759.74,
        "changePercent": -0.1038749293255971,
        "marketCap": 355542818265.04,
        "peRatio": 40.0205783729,
        "pbRatio": 16.6780569596,
        "dividendYield": 0,
        "popularityScore": 50
      },
      {
        "symbol": "KO",
        "name": "Coca-Cola Company",
        "sector": "Unknown",
        "industry": "Unknown",
        "lastPrice": 79.84,
        "changePercent": 1.1785578507160144,
        "marketCap": 343440450184.8,
        "peRatio": 26.2028267479,
        "pbRatio": 10.6761307527,
        "dividendYield": 0,
        "popularityScore": 50
      },
      {
        "symbol": "NFLX",
        "name": "Netflix Inc",
        "sector": "Unknown",
        "industry": "Unknown",
        "lastPrice": 78.67,
        "changePercent": 2.168831168831171,
        "marketCap": 333350227157.8,
        "peRatio": 30.3564452702,
        "pbRatio": 12.5246708667,
        "dividendYield": 0,
        "popularityScore": 50
      },
      {
        "symbol": "AMD",
        "name": "Advanced Micro Devices Inc",
        "sector": "Unknown",
        "industry": "Unknown",
        "lastPrice": 198.03,
        "changePercent": -1.0592055958031499,
        "marketCap": 325852514231,
        "peRatio": 75.167823352,
        "pbRatio": 5.1723442314,
        "dividendYield": 0,
        "popularityScore": 50
      },
      {
        "symbol": "CVX",
        "name": "Chevron Corp",
        "sector": "Unknown",
        "industry": "Unknown",
        "lastPrice": 184.28,
        "changePercent": 0.19028978415701317,
        "marketCap": 317829269857.68,
        "peRatio": 24.8926433159,
        "pbRatio": 1.6741690231,
        "dividendYield": 0,
        "popularityScore": 50
      },
      {
        "symbol": "CSCO",
        "name": "Cisco Systems Inc",
        "sector": "Unknown",
        "industry": "Unknown",
        "lastPrice": 79.2,
        "changePercent": 0.8146639511201635,
        "marketCap": 312926689389.6,
        "peRatio": 28.2526805155,
        "pbRatio": 6.557146227,
        "dividendYield": 0,
        "popularityScore": 50
      },
      {
        "symbol": "MRK",
        "name": "Merck & Co Inc",
        "sector": "Unknown",
        "industry": "Unknown",
        "lastPrice": 122.26,
        "changePercent": 0.32824552765469034,
        "marketCap": 305378975376.86,
        "peRatio": 16.0438675726,
        "pbRatio": 5.8896620131,
        "dividendYield": 0,
        "popularityScore": 50
      },
      {
        "symbol": "WFC",
        "name": "Wells Fargo & Company",
        "sector": "Unknown",
        "industry": "Unknown",
        "lastPrice": 88.2,
        "changePercent": -0.5636978579481398,
        "marketCap": 284145235238.3,
        "peRatio": 14.2271798137,
        "pbRatio": 1.5685286289,
        "dividendYield": 0,
        "popularityScore": 50
      },
      {
        "symbol": "GS",
        "name": "Goldman Sachs Group Inc",
        "sector": "Unknown",
        "industry": "Unknown",
        "lastPrice": 922.24,
        "changePercent": 0.6098292696230876,
        "marketCap": 279181499886.08,
        "peRatio": 17.6262074554,
        "pbRatio": 2.2441881954,
        "dividendYield": 0,
        "popularityScore": 50
      },
      {
        "symbol": "MS",
        "name": "Morgan Stanley",
        "sector": "Unknown",
        "industry": "Unknown",
        "lastPrice": 175.41,
        "changePercent": 0.5964328726271675,
        "marketCap": 278780746242.51,
        "peRatio": 17.156794033,
        "pbRatio": 2.4973192834,
        "dividendYield": 0,
        "popularityScore": 50
      },
      {
        "symbol": "RTX",
        "name": "RTX Corp",
        "sector": "Unknown",
        "industry": "Unknown",
        "lastPrice": 204.34,
        "changePercent": -0.28303728284207696,
        "marketCap": 274750986354.64,
        "peRatio": 40.8126836534,
        "pbRatio": 4.2110657729,
        "dividendYield": 0,
        "popularityScore": 50
      },
      {
        "symbol": "UNH",
        "name": "Unitedhealth Group Inc",
        "sector": "Unknown",
        "industry": "Unknown",
        "lastPrice": 288.42,
        "changePercent": -0.5448275862068911,
        "marketCap": 262645351250,
        "peRatio": 14.9323640486,
        "pbRatio": 2.7419728277,
        "dividendYield": 0,
        "popularityScore": 50
      },
      {
        "symbol": "AXP",
        "name": "American Express Company",
        "sector": "Unknown",
        "industry": "Unknown",
        "lastPrice": 346.18,
        "changePercent": 1.0302057493068817,
        "marketCap": 238466665235.54,
        "peRatio": 22.0129848828,
        "pbRatio": 7.1239369432,
        "dividendYield": 0,
        "popularityScore": 50
      },
      {
        "symbol": "MCD",
        "name": "McDonald`s Corp",
        "sector": "Unknown",
        "industry": "Unknown",
        "lastPrice": 329.23,
        "changePercent": 0.6481000275136818,
        "marketCap": 234939987805.82,
        "peRatio": 27.9191904701,
        "pbRatio": -108.6176550189,
        "dividendYield": 0,
        "popularityScore": 50
      },
      {
        "symbol": "PEP",
        "name": "PepsiCo Inc",
        "sector": "Unknown",
        "industry": "Unknown",
        "lastPrice": 164.94,
        "changePercent": 0.21264961419283937,
        "marketCap": 225529079722.68,
        "peRatio": 27.3700339469,
        "pbRatio": 11.0520964286,
        "dividendYield": 0,
        "popularityScore": 50
      },
      {
        "symbol": "INTC",
        "name": "Intel Corp",
        "sector": "Unknown",
        "industry": "Unknown",
        "lastPrice": 44.11,
        "changePercent": -1.14298520842671,
        "marketCap": 210404700000,
        "peRatio": -788.0325842697,
        "pbRatio": 1.8411170711,
        "dividendYield": 0,
        "popularityScore": 50
      },
      {
        "symbol": "C",
        "name": "Citigroup Inc",
        "sector": "Unknown",
        "industry": "Unknown",
        "lastPrice": 116,
        "changePercent": 0.3894418000865451,
        "marketCap": 207554874444,
        "peRatio": 14.508239511,
        "pbRatio": 0.9776904082,
        "dividendYield": 0,
        "popularityScore": 50
      },
      {
        "symbol": "TMO",
        "name": "Thermo Fisher Scientific Inc",
        "sector": "Unknown",
        "industry": "Unknown",
        "lastPrice": 510.93,
        "changePercent": -0.8134027022829627,
        "marketCap": 192933360982.53,
        "peRatio": 29.3658083687,
        "pbRatio": 3.7816723702,
        "dividendYield": 0,
        "popularityScore": 50
      },
      {
        "symbol": "DIS",
        "name": "Walt Disney Co (The)",
        "sector": "Unknown",
        "industry": "Unknown",
        "lastPrice": 105.58,
        "changePercent": -0.39622641509434126,
        "marketCap": 188490796360.68,
        "peRatio": 15.3844920307,
        "pbRatio": 1.7376267226,
        "dividendYield": 0,
        "popularityScore": 50
      },
      {
        "symbol": "ISRG",
        "name": "Intuitive Surgical",
        "sector": "Healthcare",
        "industry": "Unknown",
        "lastPrice": 504.05,
        "changePercent": 0.9048505595259622,
        "marketCap": 178683745595.65,
        "peRatio": 62.5643366932,
        "pbRatio": 10.0248959603,
        "dividendYield": 0,
        "popularityScore": 50
      },
      {
        "symbol": "BA",
        "name": "Boeing Company",
        "sector": "Unknown",
        "industry": "Unknown",
        "lastPrice": 230.76,
        "changePercent": -0.5473430159893161,
        "marketCap": 176364951440.04,
        "peRatio": 93.3147891217,
        "pbRatio": 32.3368081115,
        "dividendYield": 0,
        "popularityScore": 50
      },
      {
        "symbol": "CRM",
        "name": "Salesforce Inc",
        "sector": "Unknown",
        "industry": "Unknown",
        "lastPrice": 182.6,
        "changePercent": -1.3825880319723494,
        "marketCap": 176272320000,
        "peRatio": 24.4076876212,
        "pbRatio": 2.9368441046,
        "dividendYield": 0,
        "popularityScore": 50
      },
      {
        "symbol": "BLK",
        "name": "BlackRock Finance Inc",
        "sector": "Unknown",
        "industry": "Unknown",
        "lastPrice": 1093.64,
        "changePercent": 1.1430896715004557,
        "marketCap": 169353803476.68,
        "peRatio": 27.7811357409,
        "pbRatio": 3.0503756097,
        "dividendYield": 0,
        "popularityScore": 50
      },
      {
        "symbol": "UNP",
        "name": "Union Pacific Corp",
        "sector": "Unknown",
        "industry": "Unknown",
        "lastPrice": 266.1,
        "changePercent": 1.1902498383846047,
        "marketCap": 157840112562.9,
        "peRatio": 22.1126523624,
        "pbRatio": 8.5471442337,
        "dividendYield": 0,
        "popularityScore": 50
      },
      {
        "symbol": "HON",
        "name": "Honeywell International Inc",
        "sector": "Unknown",
        "industry": "Unknown",
        "lastPrice": 243.97,
        "changePercent": 1.3290692362005185,
        "marketCap": 154893432135.76,
        "peRatio": 32.7539505468,
        "pbRatio": 11.140206569,
        "dividendYield": 0,
        "popularityScore": 50
      },
      {
        "symbol": "LMT",
        "name": "Lockheed Martin Corp",
        "sector": "Unknown",
        "industry": "Unknown",
        "lastPrice": 656.27,
        "changePercent": -0.30231215629082875,
        "marketCap": 152319913194.96,
        "peRatio": 30.3607560684,
        "pbRatio": 22.6632812372,
        "dividendYield": 0,
        "popularityScore": 50
      },
      {
        "symbol": "PFE",
        "name": "Pfizer Inc.",
        "sector": "Healthcare",
        "industry": "Unknown",
        "lastPrice": 26.59,
        "changePercent": -0.2251407129455862,
        "marketCap": 151519920825,
        "peRatio": 15.4171673611,
        "pbRatio": 1.6327401733,
        "dividendYield": 0,
        "popularityScore": 50
      },
      {
        "symbol": "DHR",
        "name": "Danaher Corp",
        "sector": "Healthcare",
        "industry": "Unknown",
        "lastPrice": 209.5,
        "changePercent": -0.8284023668639053,
        "marketCap": 150012808105,
        "peRatio": 42.8240959478,
        "pbRatio": 2.9373383741,
        "dividendYield": 0,
        "popularityScore": 50
      },
      {
        "symbol": "SBUX",
        "name": "Starbucks Corp",
        "sector": "Consumer Cyclical",
        "industry": "Unknown",
        "lastPrice": 96.92,
        "changePercent": -0.5846753513180769,
        "marketCap": 110855879000,
        "peRatio": 80.975806428,
        "pbRatio": -13.2149056469,
        "dividendYield": 0,
        "popularityScore": 50
      },
      {
        "symbol": "ADBE",
        "name": "Adobe Inc.",
        "sector": "Technology",
        "industry": "Unknown",
        "lastPrice": 254.93,
        "changePercent": -1.4229921503422167,
        "marketCap": 108254146000,
        "peRatio": 15.1829096774,
        "pbRatio": 9.3137869741,
        "dividendYield": 0,
        "popularityScore": 50
      },
      {
        "symbol": "UPS",
        "name": "United Parcel Service",
        "sector": "Industrials",
        "industry": "Unknown",
        "lastPrice": 116.73,
        "changePercent": 1.0299463389302386,
        "marketCap": 99032050971.27,
        "peRatio": 17.7731606194,
        "pbRatio": 6.1029180361,
        "dividendYield": 0,
        "popularityScore": 50
      },
      {
        "symbol": "NKE",
        "name": "Nike Inc.",
        "sector": "Consumer Cyclical",
        "industry": "Unknown",
        "lastPrice": 64.95,
        "changePercent": -0.6880733944954172,
        "marketCap": 96674369140.2,
        "peRatio": 38.3020479953,
        "pbRatio": 6.8636399816,
        "dividendYield": 0,
        "popularityScore": 50
      },
      {
        "symbol": "D",
        "name": "Dominion Energy Inc",
        "sector": "Unknown",
        "industry": "Unknown",
        "lastPrice": 65.96,
        "changePercent": 0.7638252367858235,
        "marketCap": 56292481905,
        "peRatio": 24.0978090347,
        "pbRatio": 2.0328800659,
        "dividendYield": 0,
        "popularityScore": 50
      },
      {
        "symbol": "PAA",
        "name": "Plains All American Pipeline LP",
        "sector": "Unknown",
        "industry": "Unknown",
        "lastPrice": 20.89,
        "changePercent": 0.9178743961352719,
        "marketCap": 14692030002.28,
        "peRatio": 17.2037822041,
        "pbRatio": 1.5048683809,
        "dividendYield": 0,
        "popularityScore": 50
      },
      {
        "symbol": "JJSF",
        "name": "J&J Snack Foods Corp",
        "sector": "Unknown",
        "industry": "Unknown",
        "lastPrice": 84.65,
        "changePercent": -0.49371106147876753,
        "marketCap": 1637398324.7,
        "peRatio": 26.6959863813,
        "pbRatio": 1.7937054007,
        "dividendYield": 0,
        "popularityScore": 50
      },
      {
        "symbol": "RXRX",
        "name": "Recursion Pharmaceuticals Inc - Class A",
        "sector": "Unknown",
        "industry": "Unknown",
        "lastPrice": 3.4,
        "changePercent": -0.5847953216374274,
        "marketCap": 1484798249.7,
        "peRatio": -2.0750650201,
        "pbRatio": 1.4182158519,
        "dividendYield": 0,
        "popularityScore": 50
      },
      {
        "symbol": "MRTN",
        "name": "Marten Transport Ltd",
        "sector": "Unknown",
        "industry": "Unknown",
        "lastPrice": 13.9,
        "changePercent": 1.9809244314013172,
        "marketCap": 1133133893.6,
        "peRatio": 58.4692411558,
        "pbRatio": 1.4750506295,
        "dividendYield": 0,
        "popularityScore": 50
      },
      {
        "symbol": "MRT",
        "name": "MedEquities Realty Trust Inc",
        "sector": "Unknown",
        "industry": "Unknown",
        "lastPrice": 2.1,
        "changePercent": 0,
        "marketCap": 132872079.9,
        "peRatio": -6.7298837972,
        "pbRatio": -1.8161103276,
        "dividendYield": 0,
        "popularityScore": 50
      },
      {
        "symbol": "BTC-USD",
        "name": "Bitcoin USD",
        "sector": "Cryptocurrency",
        "industry": "Unknown",
        "lastPrice": 0,
        "changePercent": 0,
        "marketCap": 0,
        "peRatio": 0,
        "pbRatio": 0,
        "dividendYield": 0,
        "popularityScore": 50
      },
      {
        "symbol": "ETH-USD",
        "name": "Ethereum USD",
        "sector": "Cryptocurrency",
        "industry": "Unknown",
        "lastPrice": 0,
        "changePercent": 0,
        "marketCap": 0,
        "peRatio": 0,
        "pbRatio": 0,
        "dividendYield": 0,
        "popularityScore": 50
      },
      {
        "symbol": "MRTAX",
        "name": "MASSMUTUAL RETIRESMART BY JPMORGAN 2020 FUND CLASS A",
        "sector": "Unknown",
        "industry": "Unknown",
        "lastPrice": 10.98,
        "changePercent": 0,
        "marketCap": 0,
        "peRatio": 0,
        "pbRatio": 0,
        "dividendYield": 0,
        "popularityScore": 50
      },
      {
        "symbol": "MRTNX",
        "name": "MASSMUTUAL RETIRESMART BY JPMORGAN 2020 FUND CLASS R3",
        "sector": "Unknown",
        "industry": "Unknown",
        "lastPrice": 10.38,
        "changePercent": 0,
        "marketCap": 0,
        "peRatio": 0,
        "pbRatio": 0,
        "dividendYield": 0,
        "popularityScore": 50
      },
      {
        "symbol": "MRTI",
        "name": "Maxus Realty Trust Inc",
        "sector": "Unknown",
        "industry": "Unknown",
        "lastPrice": 90,
        "changePercent": -5.263157894736842,
        "marketCap": 0,
        "peRatio": 0,
        "pbRatio": 0,
        "dividendYield": 0,
        "popularityScore": 50
      }
    ],
    "totalStocks": 65,
    "updatedAt": "2026-02-23T14:22:25.055Z"
  },
  "timestamp": 1771856545055
}